{
    "InwardRefNo": "0000000043",
    "Error": 0,
    "data": {
        "InwardRefNo": "",
        "SourceOfDoc": "",
        "DocMailPerson": "",
        "InwardDate": "",
        "PoLpo": "",
        "GaName": "",
        "CompanyGstinPdf": "03AAGCT7889P1ZD",
        "CCompanyGstinPdf": "1,490.48,184.22,558.09,191.97",
        "CompanyGstinSap": "",
        "VendorName": "",
        "VendorGstin": "03AADCP2498P1ZX",
        "CVendorGstin": "",
        "InvoiceNo": "PGPLPBSEP0362526",
        "CInvoiceNo": "1,490.96,124.26,562.10,131.93",
        "InvoiceDate": "20250908",
        "CInvoiceDate": "38,169.84,572.00,186.35,577.25",
        "InvoiceAmount": "364838.15",
        "CInvoiceAmount": "1,559.79,448.52,589.48,454.75",
        "PoLpoIoNoPdf": "33000931",
        "CPoLpoIoNo": "21,296.03,359.37,320.78,366.36",
        "IrnNo": "78362b854a9a81f6a15d155ec0d329df7d1553994767b5ce96a8c1909296547d",
        "CIrnNo": "1,102.56,238.23,313.95,244.85",
        "MsmeNo": "",
        "Status": "Draft",
        "ModeOfEntry": "Manual",
        "CreatedOn": "20250910",
        "CreatedBy": "DEVESH",
        "ChangedOn": "20250918",
        "ChangedBy": "DEVESH",
        "FileName": "PGPLPBSEP0362526-Torrent Gas.pdf",
        "ErrorNo": "",
        "ErrorMsg": "",
        "ErrorType": "S",
        "Flag": "A",
        "DCCHEADERTODCCSES": [
            {
                "InwardRefNo": "",
                "PoNo": "0328",
                "SesGrnScrollNoPdf": "6000122072",
                "ItemNo": "1",
                "SesGrnScrollNoSap": "",
                "ParkDocNo": "",
                "Amount": "540122.00",
                "CreatedOn": "20250910",
                "Zindicator": "",
                "CreatedBy": "DEVESH",
                "CSesGrnScrollNoPdf": "1,442.84,165.64,498.88,174.57",
                "ChangedOn": "20250918",
                "ChangedBy": "DEVESH"
            },
            {
                "InwardRefNo": "",
                "PoNo": "PO 36300939",
                "SesGrnScrollNoPdf": "6000120804",
                "ItemNo": "1",
                "SesGrnScrollNoSap": "",
                "ParkDocNo": "",
                "Amount": "1874361.41",
                "CreatedOn": "20250910",
                "Zindicator": "",
                "CreatedBy": "DEVESH",
                "CSesGrnScrollNoPdf": "1,344.61,248.09,387.36,259.53",
                "ChangedOn": "20250918",
                "ChangedBy": "DEVESH"
            }
        ]
    }
}